src/__init__.py
src/dependency_graphql.py
dependency_graphql-0.0.1.dist-info/METADATA
dependency_graphql-0.0.1.dist-info/WHEEL
dependency_graphql-0.0.1.dist-info/entry_points.txt
dependency_graphql-0.0.1.dist-info/top_level.txt
dependency_graphql-0.0.1.dist-info/zip-safe
dependency_graphql-0.0.1.dist-info/RECORD
