Metadata-Version: 2.1
Name: dependency-graphql
Version: 0.0.1
Summary: Dependency graphs for GitHub repositories
Home-page: https://github.com/fionn/dependency-graphql
Author: Fionn Fitzmaurice
License: UNKNOWN
Project-URL: Source Code, https://github.com/fionn/dependency-graphql
Project-URL: Changelog, https://github.com/fionn/dependency-graphql/tags
Project-URL: Documentation, https://github.com/fionn/dependency-graphql/blob/master/README.md
Project-URL: Bug Tracker, https://github.com/fionn/dependency-graphql/issues
Project-URL: PyPI, https://pypi.org/project/dependency-graphql/
Project-URL: Download, https://github.com/fionn/dependency-graphql/archive/refs/heads/master.zip
Keywords: github,dependency graph
Platform: UNKNOWN
Classifier: Programming Language :: Python :: 3
Classifier: Development Status :: 3 - Alpha
Classifier: Intended Audience :: Developers
Classifier: Typing :: Typed
Requires-Python: >=3.7
Requires-Dist: requests
Requires-Dist: anytree
Provides-Extra: dev
Requires-Dist: pylint ; extra == 'dev'
Requires-Dist: mypy ; extra == 'dev'
Requires-Dist: types-requests ; extra == 'dev'
